pysummaries/__init__.py
pysummaries/pysummaries.py
pysummaries/sample_data.py
pysummaries/reportable/__init__.py
pysummaries/reportable/html_elements.py
pysummaries/reportable/intermediate_representation.py
pysummaries/reportable/reportable.py
pysummaries/reportable/styles.py
pysummaries/reportable/template.html
pysummaries/table_summary/__init__.py
pysummaries/table_summary/summary_fun.py
pysummaries/table_summary/table_summary.py
pysummaries/table_summary/utils.py
pysummaries-0.0.1b1.dist-info/LICENSE
pysummaries-0.0.1b1.dist-info/METADATA
pysummaries-0.0.1b1.dist-info/WHEEL
pysummaries-0.0.1b1.dist-info/top_level.txt
pysummaries-0.0.1b1.dist-info/RECORD
